LICENSE.rst
LICENSE_GPL.rst
MANIFEST.in
README.rst
setup.py
src/agx/__init__.py
src/agx.generator.dexterity.egg-info/PKG-INFO
src/agx.generator.dexterity.egg-info/SOURCES.txt
src/agx.generator.dexterity.egg-info/dependency_links.txt
src/agx.generator.dexterity.egg-info/entry_points.txt
src/agx.generator.dexterity.egg-info/namespace_packages.txt
src/agx.generator.dexterity.egg-info/not-zip-safe
src/agx.generator.dexterity.egg-info/requires.txt
src/agx.generator.dexterity.egg-info/top_level.txt
src/agx/generator/__init__.py
src/agx/generator/dexterity/__init__.py
src/agx/generator/dexterity/configure.zcml
src/agx/generator/dexterity/dxgenerator.py
src/agx/generator/dexterity/generator.rst
src/agx/generator/dexterity/gsgenerator.py
src/agx/generator/dexterity/profiles.py
src/agx/generator/dexterity/schema.py
src/agx/generator/dexterity/scope.py
src/agx/generator/dexterity/tests.py
src/agx/generator/dexterity/utils.py
src/agx/generator/dexterity/profiles/dexterity.profile.di
src/agx/generator/dexterity/profiles/dexterity.profile.notation
src/agx/generator/dexterity/profiles/dexterity.profile.uml
src/agx/generator/dexterity/resources/model_templates/dexterity_example/manifest.txt
src/agx/generator/dexterity/resources/model_templates/dexterity_example/model.di
src/agx/generator/dexterity/resources/model_templates/dexterity_example/model.notation
src/agx/generator/dexterity/resources/model_templates/dexterity_example/model.uml
src/agx/generator/dexterity/resources/model_templates/dexterity_example/model.uml.agx
src/agx/generator/dexterity/resources/model_templates/dexterity_example/uml_profiles/buildout.profile.uml
src/agx/generator/dexterity/resources/model_templates/dexterity_example/uml_profiles/dexterity.profile.uml
src/agx/generator/dexterity/resources/model_templates/dexterity_example/uml_profiles/plone.profile.uml
src/agx/generator/dexterity/resources/model_templates/dexterity_example/uml_profiles/pyegg.profile.uml
src/agx/generator/dexterity/resources/model_templates/dexterity_example/uml_profiles/zca.profile.uml
src/agx/generator/dexterity/resources/model_templates/dexterity_product/manifest.txt
src/agx/generator/dexterity/resources/model_templates/dexterity_product/model.di
src/agx/generator/dexterity/resources/model_templates/dexterity_product/model.notation
src/agx/generator/dexterity/resources/model_templates/dexterity_product/model.uml
